{
  "C291980": "Facet not working",
  "C291981": "Facet not working",
  "C299200": "Facet not working",
  "C297509": "Facet not working",
  "C277751": "setting problem APS not basic",
  "C277752": "setting problem APS not basic",
  "C277753": "setting problem APS not basic",
  "C260049": "login problem APS not basic",
  "C260051": "login problem APS not basic",
  "C279932": "login problem APS not basic",
  "C279931": "login problem APS not basic",
  "C279930": "login problem APS not basic",
  "C315268": "Attach file issue",
  "C246522": "Attach file issue",
  "C299040": "Attach file issue",
  "C286516": "Attach file issue",
  "C246534": "Attach file issue",
  "C279886": "Attach file issue",
  "C291893": "flaky test"
}

